py_appsheet/__init__.py
py_appsheet/client.py
py_appsheet/utils.py
py_appsheet-0.1.0.dist-info/LICENSE
py_appsheet-0.1.0.dist-info/METADATA
py_appsheet-0.1.0.dist-info/WHEEL
py_appsheet-0.1.0.dist-info/top_level.txt
py_appsheet-0.1.0.dist-info/RECORD
