Metadata-Version: 2.1
Name: py-appsheet
Version: 0.1.0
Summary: A no-frills Python library for interacting with the Google AppSheet API.
Home-page: https://github.com/greatscott/py-appsheet
Author: Scott Novich
Author-email: scott.novich@gmail.com
License: MIT
Classifier: Programming Language :: Python :: 3
Classifier: License :: OSI Approved :: MIT License
Classifier: Operating System :: OS Independent
Requires-Python: >=3.7
License-File: LICENSE
Requires-Dist: requests >=2.0.0
